classic/scheduler/__init__.py
classic/scheduler/decorators.py
classic/scheduler/scheduler.py
classic/scheduler/task.py
classic_scheduler-1.4.0.dist-info/licenses/LICENSE
classic_scheduler-1.4.0.dist-info/METADATA
classic_scheduler-1.4.0.dist-info/WHEEL
classic_scheduler-1.4.0.dist-info/top_level.txt
classic_scheduler-1.4.0.dist-info/RECORD
