Metadata-Version: 2.4
Name: classic-scheduler
Version: 1.4.0
Summary: Simple in-process scheduler
Author-email: Sergei Variasov <variasov@gmail.com>
License-Expression: MIT
Project-URL: Homepage, https://github.com/variasov/classic-scheduler
Requires-Python: >=3.10
License-File: LICENSE
Requires-Dist: classic-actors~=0.1
Requires-Dist: classic-components~=1.3
Requires-Dist: croniter~=3.0
Provides-Extra: dev
Requires-Dist: build~=1.2.2.post1; extra == "dev"
Requires-Dist: pytest==8.3.4; extra == "dev"
Requires-Dist: pytest-cov==6.0.0; extra == "dev"
Requires-Dist: isort==6.0.0; extra == "dev"
Requires-Dist: yapf==0.43.0; extra == "dev"
Requires-Dist: flake8==7.1.1; extra == "dev"
Requires-Dist: Flake8-pyproject==1.2.3; extra == "dev"
Dynamic: license-file
